promethean/__init__.py
promethean/__main__.py
promethean/api/__init__.py
promethean/api/command/__init__.py
promethean/api/command/command.py
promethean/api/command/command_context.py
promethean/api/command/command_manager.py
promethean/api/command/command_source.py
promethean/api/command/arguments/__init__.py
promethean/api/command/arguments/argument_type.py
promethean/api/command/arguments/bool_argument_type.py
promethean/api/command/arguments/float_argument_type.py
promethean/api/command/arguments/integer_argument_type.py
promethean/api/command/arguments/string_argument_type.py
promethean/api/command/exceptions/__init__.py
promethean/api/command/nodes/__init__.py
promethean/api/command/nodes/argument_command_node.py
promethean/api/command/nodes/command_node.py
promethean/api/command/nodes/literal_command_node.py
promethean/api/event/__init__.py
promethean/api/event/event.py
promethean/api/event/event_manager.py
promethean/api/event/exceptions/__init__.py
promethean/api/vila/__init__.py
promethean/api/vila/abc_bot.py
promethean/api/vila/abc_group.py
promethean/api/vila/abc_member.py
promethean/api/vila/abc_message.py
promethean/api/vila/abc_role.py
promethean/api/vila/abc_room.py
promethean/api/vila/abc_villa.py
promethean/cli/__init__.py
promethean/cli/cli_entry.py
promethean/cli/single/__init__.py
promethean/commands/__init__.py
promethean/commands/console_command_source.py
promethean/commands/user_command_source.py
promethean/config/__init__.py
promethean/config/multi_config_temp.py
promethean/constants/__init__.py
promethean/constants/constants.py
promethean/events/__init__.py
promethean/events/audit_callback_event.py
promethean/events/command_register_event.py
promethean/events/create_robot_event.py
promethean/events/delete_robot_event.py
promethean/events/handle_event.py
promethean/events/member_add_quick_emoticon_event.py
promethean/events/member_send_message_event.py
promethean/events/new_member_join_event.py
promethean/log/__init__.py
promethean-0.0.2.dist-info/METADATA
promethean-0.0.2.dist-info/WHEEL
promethean-0.0.2.dist-info/licenses/LICENSE
promethean-0.0.2.dist-info/RECORD
