Metadata-Version: 2.1
Name: promethean
Version: 0.0.2
Summary: Friends are fate, always cherish. To our friendship, cheers!
Project-URL: Homepage, https://github.com/Bailu-Studios/Promethean
Author-email: 古镇天Gugle <gugle@st.xatu.edu.cn>
License: GNU GENERAL PUBLIC LICENSE
License-File: LICENSE
Classifier: License :: OSI Approved :: GNU Affero General Public License v3
Classifier: Operating System :: OS Independent
Classifier: Programming Language :: Python :: 3
Requires-Python: >=3.7
Requires-Dist: aiohttp>=3.8.4
Requires-Dist: fastapi>=0.97.0
Requires-Dist: loguru>=0.7.0
Requires-Dist: uvicorn>=0.22.0
